[
	{ "s": "T", "p": [3] },
	{ "s": "TABLAS", "p": [18, 19] },
	{ "s": "TAL", "p": [20, 15] },
	{ "s": "TE", "p": [11] },
	{ "s": "TENDRÁ", "p": [14] },
	{ "s": "TENER", "p": [10, 9, 6] },
	{ "s": "TERMINO", "p": [8] },
	{ "s": "TEXT", "p": [3] },
	{ "s": "THIS", "p": [3] },
	{ "s": "TIENE", "p": [6] },
	{ "s": "TITLE", "p": [1] },
	{ "s": "TO", "p": [3] },
	{ "s": "TODAS", "p": [22, 20, 19] },
	{ "s": "TODO", "p": [4, 3, 2] },
	{ "s": "TODOS", "p": [17] },
	{ "s": "TOPIC", "p": [3] },
	{ "s": "TRABAJA", "p": [7] },
	{ "s": "TRAVÉS", "p": [22, 7] },
	{ "s": "TRAZA", "p": [22] },
	{ "s": "TÉRMINO", "p": [10, 9, 6] }
]